LICENSE-MIT
MANIFEST.in
README.rst
setup.cfg
setup.py
passbyme2fa_client/__init__.py
passbyme2fa_client/http_error.py
passbyme2fa_client/json_helper.py
passbyme2fa_client/passbyme2fa_client.py
passbyme2fa_client/passbyme_error.py
passbyme2fa_client/recipient_status.py
passbyme2fa_client/session_info.py
passbyme2fa_client/truststore.pem
passbyme2fa_client.egg-info/PKG-INFO
passbyme2fa_client.egg-info/SOURCES.txt
passbyme2fa_client.egg-info/dependency_links.txt
passbyme2fa_client.egg-info/pbr.json
passbyme2fa_client.egg-info/requires.txt
passbyme2fa_client.egg-info/top_level.txt
test/auth.pem
test/test_cancel_message.py
test/test_config.py
test/test_send_message.py
test/test_track_message.py