Metadata-Version: 1.1
Name: passbyme2fa-client
Version: 1.0.5
Summary: Messaging SDK for PassBy[ME] Mobile ID solution
Home-page: https://www.passbyme.com/
Author: Microsec ltd.
Author-email: development@passbyme.com
License: MIT
Download-URL: https://github.com/microsec/passbyme2fa-client-python
Platform: UNKNOWN
